{"id":13308,"date":"1999-02-10","title":"ratifikace Evr.charty místní samosprávy","category_id":null,"vote_summary":{"yes":56,"no":66,"abstain":66,"absent":0,"not_logged":12},"party_breakdown":{"ods":{"yes":2,"no":50,"abstain":5,"absent":0,"not_logged":6},"kdu-csl":{"yes":17,"no":0,"abstain":1,"absent":0,"not_logged":2},"cssd":{"yes":16,"no":15,"abstain":42,"absent":0,"not_logged":1},"kscm":{"yes":21,"no":0,"abstain":1,"absent":0,"not_logged":2},"us":{"yes":0,"no":1,"abstain":17,"absent":0,"not_logged":1}},"mps":[[345,1],[4,1],[346,1],[347,2],[348,1],[350,1],[352,1],[353,4],[356,1],[357,1],[358,1],[359,1],[360,1],[365,1],[261,4],[369,1],[371,0],[372,1],[373,0],[375,1],[374,1],[335,1],[67,1],[263,4],[378,1],[69,1],[383,1],[384,1],[385,1],[387,1],[391,1],[266,1],[107,2],[110,1],[111,1],[400,1],[401,1],[402,4],[405,1],[269,2],[406,1],[407,1],[127,1],[409,1],[270,1],[273,1],[275,4],[412,1],[277,1],[415,1],[418,1],[278,2],[421,1],[244,2],[164,1],[423,1],[280,1],[282,1],[429,4],[430,1],[431,1],[432,1],[285,1],[295,0],[333,0],[297,0],[54,0],[377,0],[63,0],[64,0],[390,0],[392,0],[299,4],[399,0],[340,0],[143,2],[416,4],[156,0],[301,0],[420,0],[302,0],[165,0],[193,0],[344,0],[207,2],[8,1],[349,2],[12,2],[351,1],[16,1],[203,2],[354,1],[208,2],[355,2],[209,2],[210,2],[211,2],[35,2],[362,1],[213,2],[39,1],[40,2],[363,1],[214,0],[215,0],[367,2],[370,1],[217,1],[218,2],[376,1],[219,0],[220,1],[222,2],[382,0],[77,2],[386,2],[388,2],[224,2],[225,2],[226,4],[393,0],[227,2],[229,2],[396,0],[122,1],[124,2],[410,1],[411,2],[232,2],[233,2],[234,0],[235,2],[236,0],[237,2],[413,2],[414,0],[239,1],[240,0],[241,2],[419,0],[242,2],[243,2],[245,2],[246,2],[247,2],[248,2],[422,0],[249,0],[424,0],[250,2],[426,2],[427,2],[428,1],[252,2],[196,2],[253,2],[254,0],[312,0],[206,0],[19,0],[31,0],[303,0],[361,0],[36,0],[304,2],[305,0],[366,0],[306,0],[307,0],[308,0],[379,0],[309,0],[99,4],[310,4],[105,0],[311,0],[136,0],[313,0],[162,0],[425,0],[317,0],[364,2],[380,2],[381,2],[79,2],[389,2],[91,2],[394,2],[395,2],[397,2],[368,2],[398,2],[403,2],[404,2],[408,2],[129,1],[272,2],[417,2],[181,2],[185,4]],"tisk_info":{"tisk_id":14,"obdobi":3,"nazev":"Evropská charta místní samosprávy","konecny_stav":"Schválena","temata":["evropská charta","mezinárodní charta","Rada Evropy","ratifikace dohody","územní samospráva"],"historie":["Text mezinárodní smlouvy rozeslán poslancům jako tisk 14/0 dne 21. 7. 1998.","Organizační výbor projednání mezinárodní smlouvy doporučil 23. 7. 1998 (usnesení č. 4 ). Určil zpravodaje: RNDr. Jiří Payne a navrhl přikázat k projednání výborům: Zahraniční výbor","1. Čtení proběhlo 19. 8. 1998 na 3. schůzi. Mezinárodní smlouva přikázána k projednání výborům (usnesení č. 34 ).","Zahraniční výbor projednal mezinárodní smlouvu a vydal 13. 10. 1998 usnesení doručené poslancům jako tisk 14/1 (doporučuje zamítnout) . Výbor pro veřejnou správu, regionální rozvoj a životní prostředí projednal mezinárodní smlouvu a vydal 14. 10. 1998 usnesení doručené poslancům jako tisk 14/2 (doporučuje dát souhlas s ratifikací) . Výbor pro evropskou integraci projednal navíc mezinárodní smlouvu a vydal 14. 10. 1998 usnesení doručené poslancům jako tisk 14/3 (přerušuje projednávání) . Výbor pro evropskou integraci projednal navíc mezinárodní smlouvu a vydal 14. 1. 1999 usnesení doručené poslancům jako tisk 14/4 (doporučuje dát souhlas s ratifikací) . Zahraniční výbor projednal mezinárodní smlouvu a vydal 27. 1. 1999 usnesení doručené poslancům jako tisk 14/5 . Zahraniční výbor projednal mezinárodní smlouvu a vydal 27. 1. 1999 usnesení doručené poslancům jako tisk 14/6 (doporučuje dát souhlas s ratifikací) .","2. Čtení proběhlo 10. 2. 1999 na 9. schůzi. Poslanecká sněmovna dala souhlas k ratifikaci (usnesení č. 176 ). SENÁT Mezinárodní smlouva doručena do Senátu 15. 2. 1999 . Senát mezinárodní smlouvu schválil 10. 3. 1999.","Václav Grulich předložil Senátu mezinárodní smlouvu 16. 3. 1999 jako senátní tisk 2/0 . Organizační výbor dne 18. 10. 2002 stanovil garančním výborem Výbor pro územní rozvoj, veřejnou správu a životní prostředí ( ) a přikázal tisk k projednání: Výbor pro zahraniční věci, obranu a bezpečnost ( ), Výbor pro evropskou integraci ( ). Výbor pro územní rozvoj, veřejnou správu a životní prostředí projednal návrh dne 24. 2. 1999 a přijal usnesení č. 11, které bylo rozdáno jako tisk 2/1 ( vyslovuje souhlas ). Výbor pro evropskou integraci projednal návrh dne 3. 3. 1999 a přijal usnesení č. 24, které bylo rozdáno jako tisk 2/2 ( vyslovuje souhlas ). Výbor pro zahraniční věci, obranu a bezpečnost projednal návrh dne 10. 3. 1999 a přijal usnesení č. 19, které bylo rozdáno jako tisk 2/1 ( vyslovuje souhlas ).","Organizační výbor dne 18. 10. 2002 stanovil garančním výborem Výbor pro územní rozvoj, veřejnou správu a životní prostředí ( ) a přikázal tisk k projednání: Výbor pro zahraniční věci, obranu a bezpečnost ( ), Výbor pro evropskou integraci ( ).","Výbor pro územní rozvoj, veřejnou správu a životní prostředí projednal návrh dne 24. 2. 1999 a přijal usnesení č. 11, které bylo rozdáno jako tisk 2/1 ( vyslovuje souhlas ). Výbor pro evropskou integraci projednal návrh dne 3. 3. 1999 a přijal usnesení č. 24, které bylo rozdáno jako tisk 2/2 ( vyslovuje souhlas ). Výbor pro zahraniční věci, obranu a bezpečnost projednal návrh dne 10. 3. 1999 a přijal usnesení č. 19, které bylo rozdáno jako tisk 2/1 ( vyslovuje souhlas )."],"souvisejici_tisky":[],"souvisejici_usneseni":[34,176]}}