{"id":36555,"date":"2004-09-24","title":"Úmluva o regulaci velrybářství","category_id":null,"vote_summary":{"yes":112,"no":20,"abstain":35,"absent":0,"not_logged":33},"party_breakdown":{"cssd":{"yes":50,"no":0,"abstain":7,"absent":0,"not_logged":13},"ods":{"yes":12,"no":20,"abstain":19,"absent":0,"not_logged":6},"kscm":{"yes":27,"no":0,"abstain":6,"absent":0,"not_logged":8},"kdu-csl":{"yes":15,"no":0,"abstain":3,"absent":0,"not_logged":3},"us-deu":{"yes":7,"no":0,"abstain":0,"absent":0,"not_logged":3},"Nezařazení":{"yes":1,"no":0,"abstain":0,"absent":0,"not_logged":0}},"mps":[[344,0],[349,0],[5342,0],[12,4],[5271,0],[354,0],[5263,4],[209,4],[210,0],[5297,0],[215,0],[367,0],[5252,0],[218,0],[5298,0],[219,0],[450,0],[220,4],[382,0],[5279,0],[5385,0],[77,0],[386,2],[5316,0],[225,0],[454,0],[5120,0],[226,0],[227,0],[396,2],[5386,0],[230,0],[5317,0],[5276,0],[5269,0],[5387,0],[5283,0],[5254,0],[122,2],[410,0],[411,4],[5318,4],[5265,0],[5310,0],[234,0],[235,4],[5311,0],[236,4],[237,0],[5299,4],[5255,4],[5319,4],[5320,0],[5288,4],[239,0],[419,2],[243,0],[246,4],[247,0],[5266,0],[248,2],[249,0],[5292,2],[250,2],[426,0],[5284,0],[5272,0],[252,0],[196,0],[5294,0],[345,1],[5379,0],[4,4],[347,1],[348,0],[5280,4],[5256,2],[356,1],[357,4],[358,1],[5257,2],[360,2],[5285,4],[261,4],[371,1],[372,2],[374,2],[335,0],[67,1],[378,2],[5375,0],[383,1],[5306,2],[5253,4],[266,2],[5258,0],[5300,1],[110,0],[111,1],[400,2],[401,1],[5259,0],[269,2],[406,1],[5281,2],[5277,0],[270,2],[273,2],[275,0],[5377,0],[5273,1],[412,0],[437,1],[277,1],[5378,1],[415,2],[5278,0],[5301,2],[421,1],[244,1],[5376,1],[164,2],[423,1],[280,1],[282,2],[430,2],[431,2],[5312,0],[5302,4],[312,2],[5260,2],[5295,2],[5270,4],[206,0],[5303,2],[19,4],[5307,0],[5289,2],[5261,0],[31,0],[5267,0],[303,4],[361,0],[36,0],[304,0],[305,4],[4778,0],[5293,4],[366,0],[5321,4],[5313,0],[309,2],[5274,0],[99,0],[5290,0],[5328,0],[5308,0],[5322,4],[136,0],[5381,0],[5296,0],[5282,0],[5380,0],[5275,0],[425,0],[5268,0],[317,0],[5304,0],[295,2],[333,2],[5291,4],[297,0],[5314,0],[54,0],[377,0],[63,0],[64,2],[390,0],[392,0],[340,0],[5262,0],[143,0],[416,0],[5315,4],[301,0],[420,4],[302,0],[5324,0],[5309,0],[5325,0],[5224,0],[381,0],[5286,4],[389,0],[403,4],[5305,0],[5287,0],[417,0],[5357,4],[5365,0]],"tisk_info":{"tisk_id":666,"obdobi":4,"nazev":"Úmluva o regulaci velrybářství","konecny_stav":"Schválena","temata":["Česká republika","mořský rybolov","regulace rybolovu","rybářské dohody","velryba"],"historie":["Text mezinárodní smlouvy rozeslán poslancům jako tisk 666/0 dne 13. 5. 2004.","Organizační výbor projednání mezinárodní smlouvy doporučil 27. 5. 2004 (usnesení č. 303 ). Určil zpravodaje: Jan Kavan a navrhl přikázat k projednání výborům: Zahraniční výbor","1. Čtení proběhlo 29. 6. 2004 na 33. schůzi. Mezinárodní smlouva přikázána k projednání výborům (usnesení č. 1211 ).","Zahraniční výbor projednal mezinárodní smlouvu a vydal 13. 9. 2004 usnesení doručené poslancům jako tisk 666/1 (doporučuje dát souhlas s ratifikací) .","2. Čtení proběhlo 24. 9. 2004 na 35. schůzi. Poslanecká sněmovna dala souhlas k ratifikaci (usnesení č. 1287 ).","Libor Ambrozek předložil Senátu mezinárodní smlouvu 11. 5. 2004 jako senátní tisk 361/0 . Organizační výbor dne 21. 5. 2004 stanovil garančním výborem Výbor pro územní rozvoj, veřejnou správu a životní prostředí ( ) a přikázal tisk k projednání: Výbor pro zahraniční věci, obranu a bezpečnost ( ). Výbor pro územní rozvoj, veřejnou správu a životní prostředí projednal návrh dne 2. 6. 2004 a přijal usnesení č. 87, které bylo rozdáno jako tisk 361/1 ( doporučuje dát souhlas s ratifikací ). Výbor pro zahraniční věci, obranu a bezpečnost projednal návrh dne 2. 6. 2004 a přijal usnesení č. 168, které bylo rozdáno jako tisk 361/2 ( doporučuje dát souhlas s ratifikací ). Návrh projednán dne 24. 6. 2004 na 16. schůzi Senátu. Senát dává souhlas s ratifikací (usnesení č. 478 ).","Organizační výbor dne 21. 5. 2004 stanovil garančním výborem Výbor pro územní rozvoj, veřejnou správu a životní prostředí ( ) a přikázal tisk k projednání: Výbor pro zahraniční věci, obranu a bezpečnost ( ).","Výbor pro územní rozvoj, veřejnou správu a životní prostředí projednal návrh dne 2. 6. 2004 a přijal usnesení č. 87, které bylo rozdáno jako tisk 361/1 ( doporučuje dát souhlas s ratifikací ). Výbor pro zahraniční věci, obranu a bezpečnost projednal návrh dne 2. 6. 2004 a přijal usnesení č. 168, které bylo rozdáno jako tisk 361/2 ( doporučuje dát souhlas s ratifikací ).","Návrh projednán dne 24. 6. 2004 na 16. schůzi Senátu. Senát dává souhlas s ratifikací (usnesení č. 478 ).","Souhlas obou komor Parlamentu doručen prezidentovi republiky 4. 10. 2004."],"souvisejici_tisky":[],"souvisejici_usneseni":[1211,1287]}}