{"id":7510,"date":"1996-10-02","title":"Návrh ú.zákona p.M.S.,kterým se mění 1/1993.","category_id":null,"vote_summary":{"yes":0,"no":0,"abstain":54,"absent":0,"not_logged":146},"party_breakdown":{"cssd":{"yes":0,"no":0,"abstain":17,"absent":0,"not_logged":44},"kdu-csl":{"yes":0,"no":0,"abstain":7,"absent":0,"not_logged":11},"kscm":{"yes":0,"no":0,"abstain":4,"absent":0,"not_logged":18},"oda":{"yes":0,"no":0,"abstain":4,"absent":0,"not_logged":9},"ods":{"yes":0,"no":0,"abstain":18,"absent":0,"not_logged":50},"spr-rsc":{"yes":0,"no":0,"abstain":4,"absent":0,"not_logged":14}},"mps":[[207,4],[8,4],[12,4],[16,2],[203,2],[204,4],[208,4],[209,2],[210,4],[211,2],[35,2],[212,4],[213,4],[39,4],[40,4],[214,4],[215,2],[216,4],[217,4],[218,4],[219,4],[220,4],[221,4],[222,4],[77,4],[223,2],[224,4],[225,2],[226,2],[227,4],[228,4],[229,4],[230,4],[231,4],[122,4],[124,2],[232,4],[233,2],[234,4],[235,4],[236,4],[237,2],[238,4],[239,4],[240,2],[241,2],[242,2],[243,4],[244,4],[245,4],[246,4],[247,2],[248,4],[249,4],[250,4],[194,4],[251,4],[252,2],[196,4],[253,4],[254,4],[295,2],[5,4],[296,4],[297,4],[54,4],[298,4],[63,2],[64,4],[94,4],[299,4],[95,2],[300,2],[143,4],[156,4],[301,2],[302,2],[165,4],[193,2],[312,2],[19,2],[31,4],[303,4],[36,4],[304,4],[305,4],[306,4],[307,4],[308,2],[309,4],[99,4],[310,4],[105,4],[311,4],[136,4],[313,4],[314,4],[315,4],[162,2],[316,4],[317,4],[286,2],[287,4],[288,4],[46,4],[62,4],[289,2],[290,2],[291,4],[89,4],[102,4],[292,4],[293,2],[294,4],[255,2],[256,4],[257,4],[4,2],[258,4],[13,4],[15,4],[21,4],[22,2],[259,4],[260,4],[47,4],[48,2],[261,4],[262,4],[61,4],[67,4],[263,4],[264,2],[69,4],[71,2],[72,4],[100,4],[74,4],[79,2],[265,2],[266,4],[91,2],[271,4],[107,2],[110,4],[111,2],[267,4],[268,4],[116,4],[118,2],[269,4],[128,4],[127,4],[131,4],[270,4],[129,2],[272,4],[273,4],[274,4],[275,4],[134,2],[139,4],[276,4],[277,4],[152,2],[278,4],[164,4],[170,4],[279,4],[171,4],[172,4],[280,4],[181,2],[281,4],[282,4],[185,4],[190,4],[283,4],[197,4],[284,4],[198,2],[285,2],[318,4],[319,4],[320,4],[93,4],[321,4],[322,4],[115,4],[323,4],[324,2],[325,2],[326,2],[327,4],[328,4],[180,4],[329,4],[330,4],[331,4],[332,2]],"tisk_info":{"tisk_id":11,"obdobi":2,"nazev":"Státní závěrečný účet za rok 1995","konecny_stav":"Schválena","temata":["Státní závěrečný účet","financování rozpočtu","plnění rozpočtu","státní rozpočet"],"historie":["Rozesláno všem poslancům: 18. 7. 1996 jako tisk 11/0 .","Organizační výbor zprávu přikázal 24. 7. 1996. Zpravodajem určen Jozef Wagner .","Rozpočtový výbor projednal zprávu a vydal usnesení doručené poslancům jako tisk 11/1 .","Čtení proběhlo 2. 10. 1996 na 5. schůzi. Zpráva schválena (usnesení č. 64 )."],"souvisejici_tisky":[],"souvisejici_usneseni":[64]}}