{"id":47006,"date":"2008-03-20","title":"Novela zákoníku práce","category_id":null,"vote_summary":{"yes":104,"no":16,"abstain":20,"absent":18,"not_logged":42},"party_breakdown":{"cssd":{"yes":39,"no":0,"abstain":3,"absent":3,"not_logged":26},"ods":{"yes":41,"no":6,"abstain":11,"absent":11,"not_logged":12},"kscm":{"yes":20,"no":0,"abstain":3,"absent":1,"not_logged":2},"kdu-csl":{"yes":1,"no":7,"abstain":3,"absent":2,"not_logged":0},"sz":{"yes":2,"no":1,"abstain":0,"absent":1,"not_logged":2},"Nezařazení":{"yes":1,"no":2,"abstain":0,"absent":0,"not_logged":0}},"mps":[[344,0],[5444,4],[5447,4],[5342,0],[5383,0],[5451,0],[354,0],[5452,0],[5263,4],[5454,0],[5456,4],[5457,0],[5458,0],[363,0],[5462,0],[5297,4],[5465,0],[5402,4],[218,0],[5298,2],[5469,0],[68,0],[5471,0],[5562,0],[5279,4],[5472,4],[5385,4],[386,4],[5407,0],[5474,4],[5475,4],[5477,0],[396,0],[5414,0],[5482,4],[5317,0],[5485,0],[5486,0],[122,4],[5384,4],[410,2],[5487,0],[5490,0],[5318,0],[5406,2],[5265,0],[5310,0],[235,4],[5311,4],[237,4],[5503,4],[5504,0],[5255,3],[5320,4],[5507,4],[239,4],[5508,0],[419,4],[5513,0],[5514,0],[422,0],[5517,3],[5292,0],[5519,3],[250,0],[5272,4],[5521,0],[252,4],[5415,0],[5522,4],[5294,0],[345,2],[5379,3],[4,2],[5445,0],[5446,0],[5256,0],[5448,0],[5450,0],[5453,3],[5455,0],[356,1],[5257,3],[360,1],[5459,2],[5460,4],[1296,3],[5285,4],[5463,1],[261,0],[5464,2],[371,0],[372,0],[375,0],[374,4],[5468,0],[335,0],[67,0],[5470,0],[5375,3],[383,2],[5306,3],[5473,0],[266,2],[5476,0],[5478,0],[5479,0],[5481,4],[5258,4],[5300,2],[5483,0],[5484,0],[111,0],[401,1],[5259,0],[269,0],[406,1],[5277,0],[5488,0],[273,1],[5489,0],[275,2],[5492,0],[5273,4],[5493,0],[5495,0],[5496,2],[5497,0],[5498,0],[5499,0],[5500,0],[437,3],[277,0],[5378,0],[5501,2],[415,2],[5278,4],[5505,0],[5301,3],[5509,0],[5510,0],[5511,0],[5512,0],[421,4],[5376,4],[164,4],[5515,3],[5516,4],[280,3],[5520,0],[282,4],[430,3],[5302,2],[312,0],[5295,0],[5270,0],[5307,0],[5261,2],[31,0],[5267,0],[303,0],[305,2],[4778,4],[5461,0],[366,0],[5321,0],[5313,0],[309,0],[5274,0],[5290,3],[5328,4],[5308,0],[5322,0],[5502,0],[5282,0],[5506,0],[4527,0],[5268,0],[295,1],[5449,1],[5291,1],[5314,2],[377,0],[64,1],[390,1],[340,3],[143,1],[416,3],[5326,1],[301,2],[420,2],[441,1],[5466,0],[5467,4],[5480,0],[5494,4],[5523,3],[230,1],[5491,1],[236,0]],"tisk_info":{"tisk_id":334,"obdobi":5,"nazev":"Novela zákoníku práce","konecny_stav":"Zamítnuto v 1. čtení","temata":["Vztahy pracovněprávní","Zákoník práce","pracovní doba","pracovní poměr na dobu určitou","zákoník práce"],"historie":["Návrh zákona rozeslán poslancům jako tisk 334/0 dne 18. 10. 2007.","Návrh zaslán vládě k vyjádření stanoviska 19. 10. 2007. Vláda zaslala stanovisko 15. 11. 2007. Stanovisko vlády rozesláno poslancům 15. 11. 2007 jako tisk 334/1 ( nesouhlas ).","Organizační výbor projednání návrhu zákona doporučil 15. 11. 2007 (usnesení č. 183 ). Určil zpravodaje: Ing. David Kafka a navrhl přikázat k projednání výborům: Výbor pro sociální politiku","1. Čtení proběhlo 20. 3. 2008 na 28. schůzi. Návrh zákona zamítnut (hlasování č. 224 , usnesení č. 714 )."],"souvisejici_tisky":[],"souvisejici_usneseni":[714]}}