{"id":26053,"date":"2001-07-12","title":"Návrh novely zákona o účetnictví","category_id":null,"vote_summary":{"yes":115,"no":38,"abstain":16,"absent":0,"not_logged":31},"party_breakdown":{"ods":{"yes":33,"no":9,"abstain":12,"absent":0,"not_logged":9},"kdu-csl":{"yes":0,"no":15,"abstain":3,"absent":0,"not_logged":2},"cssd":{"yes":63,"no":0,"abstain":1,"absent":0,"not_logged":10},"kscm":{"yes":19,"no":0,"abstain":0,"absent":0,"not_logged":5},"us":{"yes":0,"no":14,"abstain":0,"absent":0,"not_logged":4},"Nezařazení":{"yes":0,"no":0,"abstain":0,"absent":0,"not_logged":1}},"mps":[[345,4],[4,0],[347,2],[348,0],[350,1],[352,2],[353,2],[356,0],[357,0],[358,0],[359,1],[360,0],[5213,4],[365,0],[261,0],[369,0],[371,0],[372,0],[375,0],[374,0],[335,2],[67,2],[263,1],[5214,0],[378,0],[69,1],[383,0],[384,2],[385,0],[387,0],[391,2],[266,1],[107,0],[110,0],[111,4],[400,0],[401,4],[402,1],[405,1],[269,2],[406,0],[407,0],[127,4],[409,0],[270,1],[273,0],[275,0],[412,4],[277,0],[415,4],[418,1],[278,2],[421,2],[244,0],[164,2],[423,2],[280,0],[282,4],[429,4],[430,0],[431,0],[432,0],[285,0],[295,1],[333,1],[457,1],[297,1],[54,1],[377,1],[63,4],[64,1],[390,2],[392,1],[399,1],[340,1],[143,1],[416,2],[156,1],[301,1],[420,2],[302,1],[165,4],[193,1],[344,0],[8,0],[349,0],[12,0],[351,4],[16,4],[203,0],[354,0],[208,0],[355,0],[209,4],[210,0],[211,0],[35,0],[362,4],[213,4],[39,0],[40,0],[363,0],[214,0],[215,0],[367,0],[370,0],[217,0],[218,0],[376,0],[219,0],[220,0],[222,0],[382,0],[77,0],[386,4],[388,2],[224,0],[225,0],[226,4],[393,0],[227,0],[229,0],[396,0],[5193,0],[122,0],[124,0],[410,0],[411,0],[232,0],[233,0],[234,0],[235,0],[236,0],[237,0],[413,0],[414,0],[239,0],[240,0],[241,0],[419,4],[242,0],[243,0],[245,0],[246,0],[247,0],[248,0],[422,0],[249,0],[424,0],[250,0],[426,0],[427,0],[428,0],[252,4],[196,0],[253,4],[254,0],[312,0],[206,0],[19,0],[31,0],[303,0],[361,0],[36,0],[304,4],[305,0],[366,0],[306,0],[307,0],[308,0],[379,0],[309,0],[99,0],[310,4],[105,4],[311,4],[136,0],[313,0],[162,0],[425,4],[317,0],[364,1],[380,1],[381,1],[79,4],[389,1],[91,1],[395,1],[397,1],[368,4],[398,1],[403,1],[404,1],[408,1],[129,1],[272,1],[417,4],[181,4],[185,1],[394,4]],"tisk_info":{"tisk_id":852,"obdobi":3,"nazev":"Návrh novely zákona o účetnictví","konecny_stav":"Schváleno","temata":["Finance","Informační služby","Kultura","Národní hospodářství","Občan","Peněžnictví a pojišťovnictví","Pracovní síla","evropský účetní systém","finanční účetnictví","účetnictví"],"historie":["Skupina poslanců ( Bohuslav Sobotka , Martin Kocourek , Milan Ekert , Michal Kraus , Michal Doktor ) předložila sněmovně návrh zákona 14. 2. 2001. Zástupce navrhovatele: Sobotka Bohuslav a další.","Návrh zákona rozeslán poslancům jako tisk 852/0 dne 15. 2. 2001.","Návrh zaslán vládě k vyjádření stanoviska 16. 2. 2001. Vláda zaslala stanovisko 16. 3. 2001. Stanovisko vlády rozesláno poslancům 19. 3. 2001 jako tisk 852/1 ( připomínky ).","Organizační výbor projednání návrhu zákona doporučil 22. 3. 2001 (usnesení č. 387 ). Určil zpravodaje: Ing. Libor Ježek a navrhl přikázat k projednání výborům: Rozpočtový výbor","1. Čtení proběhlo 11. 4. 2001 na 35. schůzi. Návrh zákona přikázán k projednání výborům (usnesení č. 1538 ).","Rozpočtový výbor projednal návrh zákona a vydal 18. 6. 2001 usnesení doručené poslancům jako tisk 852/2 .","2. Čtení Návrh zákona prošel obecnou rozpravou 26. 6. 2001 na 37. schůzi. Návrh zákona prošel podrobnou rozpravou 26. 6. 2001 na 37. schůzi. Podané pozměňovací návrhy zpracovány jako tisk 852/3 , který byl rozeslán 29. 6. 2001 v 11:00.","3. Čtení proběhlo 12. 7. 2001 na 37. schůzi. Návrh zákona schválen (hlasování č. 326 , usnesení č. 1699 ).","Poslanecká sněmovna postoupila dne 11. 10. 2002 návrh zákona Senátu jako tisk 98 , dokument 98/0 .","Organizační výbor dne 11. 10. 2002 stanovil garančním výborem Výbor pro hospodářství, zemědělství a dopravu ( ).","Výbor pro hospodářství, zemědělství a dopravu projednal návrh dne 1. 8. 2001 a přijal usnesení č. 102, které bylo rozdáno jako tisk 98/1 ( pozměňovací návrhy ).","O návrhu zákona vráceném Senátem hlasováno 18. 9. 2001 na 38. schůzi. Sněmovna setrvala na původním návrhu zákona (hlasování č. 23 , usnesení č. 1720 ).","Zákon doručen prezidentovi k podepsání 19. 9. 2001. Prezident zákon podepsal . Rozhodnutí doručeno do Sněmovny 24. 9. 2001.","Schválený zákon odeslán k publikaci ve Sbírce zákonů 26. 9. 2001."],"souvisejici_tisky":[],"souvisejici_usneseni":[1538,1699,1720]}}