{"id":7870,"date":"1996-12-10","title":"Návrh na změny ve složení výborů PS","category_id":null,"vote_summary":{"yes":160,"no":0,"abstain":20,"absent":0,"not_logged":20},"party_breakdown":{"cssd":{"yes":54,"no":0,"abstain":1,"absent":0,"not_logged":6},"kdu-csl":{"yes":14,"no":0,"abstain":1,"absent":0,"not_logged":3},"kscm":{"yes":22,"no":0,"abstain":0,"absent":0,"not_logged":0},"oda":{"yes":9,"no":0,"abstain":0,"absent":0,"not_logged":4},"ods":{"yes":61,"no":0,"abstain":1,"absent":0,"not_logged":6},"spr-rsc":{"yes":0,"no":0,"abstain":17,"absent":0,"not_logged":1}},"mps":[[207,0],[8,0],[12,0],[16,4],[203,0],[204,0],[208,0],[209,0],[210,0],[211,0],[35,0],[212,0],[213,0],[39,4],[40,0],[214,0],[215,0],[216,0],[217,0],[218,0],[219,4],[220,0],[221,4],[222,0],[77,0],[223,0],[224,0],[225,0],[226,0],[227,0],[228,0],[229,0],[230,0],[231,0],[122,0],[124,0],[232,0],[233,0],[234,0],[235,0],[236,0],[237,0],[238,0],[239,0],[240,0],[241,4],[242,0],[243,0],[244,0],[245,0],[246,0],[247,0],[248,2],[249,0],[250,0],[194,0],[251,0],[252,0],[196,4],[253,0],[254,0],[295,4],[296,0],[333,0],[297,0],[54,0],[298,0],[63,2],[64,4],[94,0],[299,0],[95,4],[300,0],[143,0],[156,0],[301,0],[302,0],[165,0],[193,0],[312,0],[19,0],[31,0],[303,0],[36,0],[304,0],[305,0],[306,0],[307,0],[308,0],[309,0],[99,0],[310,0],[105,0],[311,0],[136,0],[313,0],[314,0],[315,0],[162,0],[316,0],[317,0],[286,0],[287,4],[288,4],[46,0],[62,4],[289,0],[290,4],[291,0],[89,0],[102,0],[292,0],[293,0],[294,0],[255,0],[256,0],[257,0],[4,0],[258,0],[13,0],[15,0],[21,0],[22,0],[259,0],[260,0],[47,0],[48,0],[261,4],[262,0],[61,0],[67,0],[263,0],[264,4],[69,0],[71,0],[72,0],[100,0],[74,0],[79,0],[265,0],[266,0],[91,0],[271,2],[107,0],[110,0],[111,0],[267,0],[268,0],[116,0],[118,0],[269,4],[128,0],[127,0],[131,0],[270,0],[129,0],[272,0],[273,0],[274,0],[275,4],[134,0],[139,0],[276,0],[277,0],[152,0],[278,0],[164,0],[170,0],[279,0],[171,0],[172,0],[280,0],[181,0],[281,0],[282,0],[185,0],[190,4],[283,0],[197,0],[284,4],[198,0],[285,0],[318,2],[319,2],[320,2],[93,2],[321,2],[322,2],[115,2],[323,2],[324,2],[325,2],[326,4],[327,2],[328,2],[180,2],[329,2],[330,2],[331,2],[332,2]],"tisk_info":{"tisk_id":103,"obdobi":2,"nazev":"Návrh novely zákona o Ústavním soudu","konecny_stav":"Vzat zpět v 1. čtení","temata":["Referendum","Ústavní soud","referendum","rozhodovací pravomoc","soudní řízení","ústavní soud"],"historie":["Skupina poslanců ( Vojtěch Filip , Dalibor Matulka , Zuzka Bebarová Rujbrová ) předložila sněmovně návrh zákona 10. 12. 1996. Zástupce navrhovatele: Filip Vojtěch.","Návrh zákona rozeslán poslancům jako tisk 103/0 dne 11. 12. 1996.","Návrh zaslán vládě k vyjádření stanoviska 13. 12. 1996. Vláda zaslala stanovisko 10. 1. 1997. Stanovisko vlády rozesláno poslancům 10. 1. 1997 jako tisk 103/1 ( nesouhlas ).","Organizační výbor projednání návrhu zákona doporučil 16. 1. 1997. Určil zpravodaje: Marek Benda a navrhl přikázat k projednání výborům: Ústavně právní výbor","1. Čtení Návrh zákona vzat zpět 25. 2. 1997 ."],"souvisejici_tisky":[],"souvisejici_usneseni":[]}}