{"id":45085,"date":"2007-03-21","title":"Novela z. o pohonných hmotách","category_id":null,"vote_summary":{"yes":177,"no":5,"abstain":8,"absent":6,"not_logged":4},"party_breakdown":{"cssd":{"yes":66,"no":0,"abstain":5,"absent":1,"not_logged":0},"ods":{"yes":76,"no":0,"abstain":2,"absent":1,"not_logged":2},"kscm":{"yes":22,"no":0,"abstain":0,"absent":2,"not_logged":2},"kdu-csl":{"yes":11,"no":0,"abstain":0,"absent":2,"not_logged":0},"sz":{"yes":0,"no":5,"abstain":1,"absent":0,"not_logged":0},"Nezařazení":{"yes":2,"no":0,"abstain":0,"absent":0,"not_logged":0}},"mps":[[344,0],[5444,0],[5447,2],[5342,0],[5383,0],[5451,0],[354,0],[5452,0],[5263,3],[5454,0],[5456,0],[5457,0],[5458,0],[363,0],[5462,0],[5297,0],[5465,0],[5402,0],[218,0],[5298,2],[5469,0],[68,0],[5471,0],[5562,0],[5279,0],[5472,0],[5385,0],[386,0],[5407,0],[5474,0],[5475,0],[5477,0],[396,0],[5414,0],[5482,0],[5317,0],[5485,0],[5486,2],[122,0],[5384,2],[410,0],[5487,0],[5490,0],[5318,0],[5406,0],[5265,0],[5310,0],[235,0],[5311,0],[236,2],[237,0],[5503,0],[5504,0],[5255,0],[5320,0],[5507,0],[239,0],[5508,0],[419,0],[5513,0],[5514,0],[422,0],[5517,0],[5292,0],[5519,0],[250,0],[5272,0],[5521,0],[252,0],[5415,0],[5522,0],[5294,0],[345,0],[5379,0],[4,0],[5445,0],[5446,0],[5256,0],[5448,0],[5450,0],[5453,0],[5455,0],[356,0],[5257,0],[360,0],[5459,0],[5460,0],[1296,3],[5285,0],[5463,0],[261,0],[5464,0],[371,0],[372,0],[375,0],[374,0],[5468,0],[335,0],[67,0],[5470,0],[5375,0],[383,0],[5306,0],[5473,0],[266,0],[5476,0],[5478,0],[5479,0],[5481,0],[5258,0],[5300,4],[5483,0],[5484,0],[111,0],[401,0],[5259,0],[269,0],[406,0],[5277,0],[5488,0],[273,0],[5489,0],[275,0],[5492,0],[5273,0],[5493,0],[5495,0],[5496,0],[5497,0],[5498,0],[5499,0],[5500,0],[437,0],[277,0],[5378,0],[5501,0],[415,0],[5278,0],[5505,0],[5301,0],[5509,0],[5510,0],[5511,2],[5512,0],[421,0],[5376,0],[164,4],[5515,0],[5516,0],[280,0],[5520,0],[282,2],[430,0],[5302,4],[312,0],[5295,0],[5270,0],[5307,0],[5261,0],[31,0],[5267,0],[303,0],[305,4],[4778,0],[5461,0],[366,0],[5321,3],[5313,0],[309,0],[5274,0],[5290,0],[5328,0],[5308,3],[5322,0],[5502,0],[5282,0],[5506,0],[4527,0],[5268,0],[295,0],[5449,0],[5291,0],[5314,0],[377,0],[64,0],[390,0],[340,3],[143,3],[416,0],[5326,0],[301,0],[420,0],[441,1],[5466,1],[5467,1],[5480,1],[5494,2],[5523,1],[230,0],[5491,0]],"tisk_info":{"tisk_id":111,"obdobi":5,"nazev":"Novela z. o pohonných hmotách","konecny_stav":"Schváleno","temata":["Paliva a maziva","Zákon stavební","Doprava a spoje","Informační služby","Kultura","Mezinárodní styky","Národní hospodářství","Občan","Obchod","Obrana a bezpečnost","Peněžnictví a pojišťovnictví","Politika","Pracovní síla","Školství","Státní správa a justice","Těžba a výroba","Věda","Zdravotnictví","Životní prostředí","benzin","motorové palivo","prodej","statistika obchodu","zemní plyn"],"historie":["Návrh zákona rozeslán poslancům jako tisk 111/0 dne 12. 12. 2006. Navrhovatel navrhl sněmovně projednávání návrhu zákona tak, aby sněmovna s ním mohla vyslovit souhlas již v prvém čtení ( § 90 odstavec 2 zákona č. 90/1995 Sb , o jednacím řádu Poslanecké sněmovny, ve znění pozdějších předpisů).","Návrh zaslán vládě k vyjádření stanoviska 13. 12. 2006. Vláda zaslala stanovisko 10. 1. 2007. Stanovisko vlády rozesláno poslancům 10. 1. 2007 jako tisk 111/1 ( připomínky ).","Organizační výbor projednání návrhu zákona doporučil 11. 1. 2007 (usnesení č. 61 ). Určil zpravodaje: Ing. Milan Urban a navrhl přikázat k projednání výborům: Hospodářský výbor","1. Čtení Návrh byl projednán v obecné rozpravě 31. 1. 2007 na 11. schůzi. Sněmovna nesouhlasila s projednáváním tak, aby mohla s návrhem zákona vyslovit souhlas již v prvém čtení. Projednávání pokračovalo 31. 1. 2007 na 11. schůzi. Návrh zákona přikázán k projednání výborům (usnesení č. 176 ). Lhůta k projednání výbory byla určena na 30 dní .","Zemědělský výbor projednal návrh zákona a vydal 22. 2. 2007 usnesení doručené poslancům jako tisk 111/2 (doporučuje schválit) . Hospodářský výbor projednal návrh zákona a vydal 2. 3. 2007 usnesení doručené poslancům jako tisk 111/3 (pozměňovací návrhy) .","2. Čtení Návrh zákona prošel obecnou rozpravou 13. 3. 2007 na 13. schůzi. Návrh zákona prošel podrobnou rozpravou 13. 3. 2007 na 13. schůzi. Podané pozměňovací návrhy zpracovány jako tisk 111/4 , který byl rozeslán 14. 3. 2007 v 11:40.","3. Čtení proběhlo 21. 3. 2007 na 13. schůzi. Návrh zákona schválen (hlasování č. 123 , usnesení č. 261 ).","Poslanecká sněmovna postoupila dne 30. 3. 2007 návrh zákona Senátu jako tisk 42 , dokument 42/0 .","Organizační výbor dne 5. 4. 2007 stanovil garančním výborem Výbor pro hospodářství, zemědělství a dopravu ( ).","Výbor pro hospodářství, zemědělství a dopravu projednal návrh dne 11. 4. 2007 a přijal usnesení č. 78, které bylo rozdáno jako tisk 42/1 ( schvaluje ).","Návrh projednán dne 12. 4. 2007 na 5. schůzi Senátu. Senát návrh schválil (usnesení č. 92 ).","Zákon doručen prezidentovi k podepsání 18. 4. 2007. Prezident zákon podepsal . Rozhodnutí doručeno do Sněmovny 25. 4. 2007.","Schválený zákon odeslán k publikaci ve Sbírce zákonů 4. 5. 2007."],"souvisejici_tisky":[],"souvisejici_usneseni":[176,261]}}