{"id":37356,"date":"2004-11-24","title":"Novela z. o poštovních službách - EU","category_id":null,"vote_summary":{"yes":15,"no":101,"abstain":69,"absent":5,"not_logged":10},"party_breakdown":{"cssd":{"yes":4,"no":42,"abstain":19,"absent":2,"not_logged":3},"ods":{"yes":0,"no":49,"abstain":2,"absent":1,"not_logged":5},"kscm":{"yes":0,"no":5,"abstain":35,"absent":1,"not_logged":0},"kdu-csl":{"yes":5,"no":4,"abstain":10,"absent":0,"not_logged":2},"us-deu":{"yes":6,"no":0,"abstain":3,"absent":1,"not_logged":0},"Nezařazení":{"yes":0,"no":1,"abstain":0,"absent":0,"not_logged":0}},"mps":[[344,1],[349,3],[5342,1],[5271,1],[354,1],[5263,1],[209,3],[210,2],[363,1],[5297,1],[215,1],[367,1],[5252,1],[218,2],[5298,1],[219,2],[450,2],[220,1],[382,1],[5279,1],[5385,1],[77,2],[386,2],[5316,2],[225,1],[454,2],[5120,2],[226,1],[227,1],[396,2],[5386,2],[230,1],[5317,2],[5276,1],[5269,4],[5387,1],[5283,1],[5254,1],[122,1],[410,2],[5318,1],[5265,2],[5310,1],[234,0],[235,4],[5311,1],[236,1],[237,0],[5299,1],[5255,2],[5319,1],[5320,1],[5288,2],[239,1],[419,0],[243,1],[246,1],[247,1],[5266,1],[248,0],[249,1],[5292,1],[250,1],[426,2],[5284,2],[5388,1],[5272,1],[252,2],[196,1],[5294,4],[345,1],[5379,1],[4,1],[347,1],[348,1],[5280,1],[5256,2],[356,1],[357,1],[358,1],[5257,1],[360,1],[5285,1],[261,1],[371,1],[372,1],[374,4],[335,1],[67,1],[378,1],[5375,1],[383,1],[5306,1],[5253,4],[266,3],[5258,4],[5300,1],[110,1],[111,1],[400,4],[401,1],[5259,1],[269,1],[406,1],[5281,1],[5277,1],[270,1],[273,1],[275,1],[5377,1],[5273,1],[412,1],[437,1],[277,1],[5378,1],[415,1],[5278,1],[5301,1],[421,1],[244,4],[5376,1],[164,2],[423,1],[280,1],[282,1],[430,1],[431,1],[5312,2],[5302,2],[312,2],[5260,2],[5295,2],[5270,2],[206,2],[5303,2],[19,2],[5307,2],[5289,2],[5261,1],[31,2],[5267,2],[303,2],[361,1],[36,1],[304,2],[305,2],[4778,2],[5293,2],[366,2],[5321,2],[5313,2],[309,2],[5274,2],[99,2],[5290,2],[5328,1],[5308,2],[5322,2],[136,2],[5381,1],[5296,2],[5282,2],[5380,3],[5275,2],[425,2],[5268,2],[317,2],[5304,2],[295,4],[333,2],[5291,2],[297,1],[5314,0],[54,2],[377,2],[63,2],[64,1],[390,2],[392,2],[340,2],[5262,2],[143,2],[416,0],[5315,1],[301,4],[420,1],[302,0],[5324,0],[5309,0],[5325,0],[5224,0],[381,2],[5286,2],[389,0],[403,3],[5305,0],[5287,0],[417,2],[5357,0],[5365,1]],"tisk_info":{"tisk_id":349,"obdobi":4,"nazev":"Novela ústavního z. Ústava České republiky","konecny_stav":"Neschváleno","temata":["Kontrola","Parlament České republiky","Péče o zdraví","Poslanci","Prezident republiky","Ústava České republiky","Ústavní soud","Zákonodárná činnost Parlamentu","kompetence parlamentu","poslanecký mandát","prezidentské volby","trestní řízení","trestní stíhání","ústava"],"historie":["Vláda předložila sněmovně návrh zákona 10. 6. 2003. Zástupce navrhovatele: ministr spravedlnosti.","Návrh zákona rozeslán poslancům jako tisk 349/0 dne 11. 6. 2003.","Organizační výbor projednání návrhu zákona doporučil 12. 6. 2003 (usnesení č. 155 ). Určil zpravodaje: JUDr. Zdeněk Koudelka, Ph.D. a navrhl přikázat k projednání výborům: Ústavně právní výbor","1. Čtení proběhlo 3. , 8. 7. 2003 na 18. schůzi. Projednávání návrhu bylo přerušeno (hlasování č. 410 , usnesení č. 616 ).","Dočasná komise pro otázky Ústavy České republiky projednala návrh zákona a vydala 4. 5. 2004 usnesení doručené poslancům jako tisk 349/1 (pozměňovací návrhy) .","Ústavně právní výbor projednal návrh zákona a vydal 17. 9. 2004 usnesení doručené poslancům jako tisk 349/2 (komplexní pozměňující návrh) .","2. Čtení Návrh zákona prošel obecnou rozpravou 21. 9. 2004 na 35. schůzi. Návrh zákona prošel podrobnou rozpravou 21. 9. 2004 na 35. schůzi. Podané pozměňovací návrhy zpracovány jako tisk 349/3 , který byl rozeslán 24. 9. 2004.","3. Čtení proběhlo 5. 11. 2004 na 37. schůzi.Návrh zákona vrácen k opakování 2. čtení (hlasování č. 147 , usnesení č. 1357 ).","Dočasná komise pro otázky Ústavy České republiky projednala návrh zákona a vydala 24. 11. 2004 usnesení doručené poslancům jako tisk 349/4 (pozměňovací návrhy) .","2. Čtení Návrh zákona prošel obecnou rozpravou 26. 11. 2004 na 38. schůzi. Návrh zákona prošel podrobnou rozpravou 26. 11. 2004 na 38. schůzi. Podané pozměňovací návrhy zpracovány jako tisk 349/5 , který byl rozeslán 6. 12. 2004.","3. Čtení proběhlo 15. 12. 2004 na 39. schůzi. Návrh zákona nebyl schválen (hlasování č. 355 )."],"souvisejici_tisky":[],"souvisejici_usneseni":[616,1122,1357]}}