{"id":52217,"date":"2010-04-14","title":"Vl.n.z. o veřejných službách v přepravě cestujících - EU","category_id":null,"vote_summary":{"yes":170,"no":0,"abstain":4,"absent":5,"not_logged":21},"party_breakdown":{"cssd":{"yes":62,"no":0,"abstain":0,"absent":1,"not_logged":7},"ods":{"yes":64,"no":0,"abstain":3,"absent":3,"not_logged":8},"kscm":{"yes":25,"no":0,"abstain":0,"absent":0,"not_logged":1},"kdu-csl":{"yes":8,"no":0,"abstain":0,"absent":1,"not_logged":0},"sz":{"yes":3,"no":0,"abstain":0,"absent":0,"not_logged":1},"Nezařazení":{"yes":8,"no":0,"abstain":1,"absent":0,"not_logged":4}},"mps":[[344,0],[5444,0],[5865,0],[5447,4],[5342,0],[5383,0],[5451,0],[354,0],[5452,0],[5263,0],[5456,0],[5430,0],[5769,0],[5458,0],[363,0],[5021,0],[5462,0],[5465,4],[5402,0],[218,0],[5469,0],[68,0],[5771,0],[5562,0],[5279,4],[5472,0],[5385,0],[386,0],[5407,0],[5475,0],[5477,0],[5414,0],[5482,0],[5317,0],[5774,0],[5775,4],[5485,0],[5486,0],[122,0],[5384,0],[410,0],[5487,0],[5490,4],[5406,0],[5310,0],[235,0],[5886,0],[5311,0],[237,0],[5503,0],[5504,0],[5255,0],[5320,0],[5507,0],[239,0],[5508,0],[419,4],[5513,0],[422,4],[5292,0],[5519,0],[5866,0],[250,0],[5284,0],[5388,0],[5272,0],[252,0],[5415,3],[5522,0],[5294,0],[345,0],[5379,0],[4,0],[5445,0],[5446,0],[5256,0],[5448,0],[5450,0],[5453,0],[5455,0],[356,3],[5257,0],[360,0],[5459,0],[5460,0],[1296,0],[5285,0],[5868,0],[5463,0],[261,0],[5464,0],[372,0],[5767,0],[5766,0],[375,0],[374,4],[5468,0],[5883,0],[67,0],[5470,4],[5375,0],[383,0],[5306,0],[5473,0],[266,3],[5476,0],[5478,4],[5479,0],[5481,0],[5258,0],[5300,4],[5483,0],[111,0],[401,2],[5259,0],[5867,0],[269,0],[406,0],[5277,0],[5488,4],[273,0],[5489,0],[275,3],[5492,4],[5273,0],[5493,0],[5495,0],[5497,0],[5498,0],[5499,0],[5500,0],[437,2],[5501,0],[415,0],[5278,0],[5505,0],[5301,0],[5509,0],[5510,4],[5511,4],[5512,0],[421,0],[5376,0],[5516,0],[280,0],[5520,2],[282,0],[430,0],[5768,0],[312,0],[5295,0],[5270,0],[5307,4],[5261,0],[31,0],[5267,0],[303,0],[305,0],[4778,0],[5461,0],[366,0],[5321,0],[5313,0],[309,0],[5274,0],[5290,0],[5328,0],[5308,0],[5322,0],[5502,0],[5282,0],[5506,0],[4527,0],[5268,0],[295,0],[5449,0],[333,0],[5291,0],[5314,0],[64,0],[390,3],[416,0],[301,0],[441,0],[5466,0],[5480,0],[5494,4],[5454,0],[5819,0],[5467,4],[377,4],[230,0],[340,0],[5496,0],[143,4],[5378,2],[236,0],[164,4],[5521,0],[5523,0]],"tisk_info":{"tisk_id":1054,"obdobi":5,"nazev":"Vl.n.z. o veřejných službách v přepravě cestujících - EU","konecny_stav":"Schváleno","temata":["Doprava","Evropská unie /EU/","Funkcionáři Poslanecké sněmovny","Obchod a služby","Doprava a spoje","Mezinárodní styky","Národní hospodářství","Občan","Státní správa a justice","cestující veřejnost","dopravní infrastruktura","osobní doprava","silniční doprava","veřejná služba","železniční doprava"],"historie":["Vláda předložila sněmovně návrh zákona 24. 2. 2010. Zástupce navrhovatele: ministr dopravy.","Návrh zákona rozeslán poslancům jako tisk 1054/0 dne 26. 2. 2010. Navrhovatel navrhl sněmovně projednávání návrhu zákona tak, aby sněmovna s ním mohla vyslovit souhlas již v prvém čtení ( § 90 odstavec 2 zákona č. 90/1995 Sb , o jednacím řádu Poslanecké sněmovny, ve znění pozdějších předpisů).","Organizační výbor projednání návrhu zákona doporučil 25. 2. 2010 (usnesení č. 480 ). Určil zpravodaje: Mgr. Oldřich Vojíř, Ph.D. a navrhl přikázat k projednání výborům: Hospodářský výbor","1. Čtení Návrh projednán v obecné rozpravě 12. 3. 2010 na 75. schůzi. Sněmovna nesouhlasila s projednáváním tak, aby mohla s návrhem zákona vyslovit souhlas již v prvém čtení. Čtení proběhlo 12. 3. 2010 na 75. schůzi. Návrh zákona přikázán k projednání výborům (usnesení č. 1624 ). Lhůta k projednání výbory byla určena na 4 dny .","Hospodářský výbor projednal návrh zákona a vydal 16. 3. 2010 usnesení doručené poslancům jako tisk 1054/1 (pozměňovací návrhy) .","2. Čtení Návrh zákona prošel obecnou rozpravou 17. 3. 2010 na 75. schůzi. Návrh zákona prošel podrobnou rozpravou 17. 3. 2010 na 75. schůzi. Podané pozměňovací návrhy zpracovány jako tisk 1054/2 , který byl rozeslán 18. 3. 2010.","3. Čtení proběhlo 14. 4. 2010 na 78. schůzi. Návrh zákona schválen (hlasování č. 57 , usnesení č. 1665 ).","Poslanecká sněmovna postoupila dne 23. 4. 2010 návrh zákona Senátu jako tisk 280 , dokument 280/0 .","Organizační výbor dne 28. 4. 2010 stanovil garančním výborem Výbor pro hospodářství, zemědělství a dopravu ( ).","Výbor pro hospodářství, zemědělství a dopravu projednal návrh dne 19. 5. 2010 a přijal usnesení č. 319, které bylo rozdáno jako tisk 280/1 ( schvaluje ).","Návrh projednán dne 20. 5. 2010 na 19. schůzi Senátu. Senát návrh schválil (usnesení č. 502 ).","Zákon doručen prezidentovi k podepsání 27. 5. 2010. Prezident zákon podepsal . Rozhodnutí doručeno do Sněmovny 7. 6. 2010.","Schválený zákon odeslán k publikaci ve Sbírce zákonů 9. 6. 2010."],"souvisejici_tisky":[],"souvisejici_usneseni":[1624,1665]}}