{"id":59704,"date":"2014-09-24","title":"Novela z. o pomoci v hmotné nouzi","category_id":null,"vote_summary":{"yes":102,"no":49,"abstain":6,"absent":31,"not_logged":12},"party_breakdown":{"cssd":{"yes":41,"no":0,"abstain":0,"absent":9,"not_logged":0},"ano":{"yes":24,"no":5,"abstain":3,"absent":8,"not_logged":7},"kscm":{"yes":28,"no":0,"abstain":0,"absent":5,"not_logged":0},"top09-s":{"yes":0,"no":20,"abstain":0,"absent":3,"not_logged":3},"ods":{"yes":0,"no":13,"abstain":0,"absent":2,"not_logged":1},"kdu-csl":{"yes":9,"no":0,"abstain":2,"absent":3,"not_logged":0},"usvit":{"yes":0,"no":11,"abstain":1,"absent":1,"not_logged":1}},"mps":[[467,0],[5891,0],[6002,0],[6136,0],[6182,0],[5447,0],[5342,0],[354,0],[5456,0],[5911,0],[6268,0],[5462,0],[6194,3],[5918,3],[5921,0],[6200,3],[5926,0],[6113,0],[5402,0],[6206,0],[68,0],[6212,0],[5433,0],[5279,0],[5269,0],[5991,0],[6173,0],[5487,0],[6232,3],[5490,0],[5960,0],[5310,3],[5965,0],[237,3],[5999,0],[6238,0],[6284,0],[5507,0],[5513,0],[6239,0],[422,0],[5979,0],[5980,3],[5866,0],[5272,0],[6160,0],[252,3],[6157,0],[5987,3],[5989,0],[6150,4],[6151,0],[6177,0],[6180,0],[6143,0],[6184,4],[6185,0],[6187,0],[6189,1],[6190,0],[6192,0],[6139,1],[6196,0],[6199,4],[6201,0],[6203,3],[6209,2],[6211,3],[6140,4],[6246,0],[6215,1],[6219,4],[6221,2],[6174,0],[6172,3],[6225,3],[6230,0],[6231,0],[6171,0],[6202,3],[6235,0],[6158,0],[6226,0],[6153,3],[6236,0],[6237,1],[443,0],[6144,3],[6168,3],[6167,4],[6166,0],[6165,2],[6163,0],[6162,0],[6161,0],[6156,4],[5718,1],[5768,3],[6149,0],[312,0],[6183,0],[5307,0],[6188,3],[5261,0],[303,0],[305,0],[4778,0],[5461,0],[5920,3],[5934,0],[5313,0],[309,0],[6279,0],[6220,3],[5290,0],[5938,0],[5948,3],[6223,0],[6224,0],[5322,0],[6228,0],[6233,0],[5962,0],[5502,0],[5282,0],[5506,0],[6169,0],[6164,0],[5268,0],[6159,0],[5897,1],[5909,1],[5914,1],[5917,1],[5919,1],[5922,1],[377,4],[5939,4],[5940,1],[6213,1],[6214,1],[6216,1],[5943,3],[5476,1],[392,1],[6176,3],[6227,1],[5955,1],[6147,1],[6280,1],[5957,1],[5558,3],[5964,1],[6240,1],[6137,4],[6154,1],[5700,3],[4,1],[346,1],[6181,1],[6079,1],[5903,3],[6074,1],[5990,1],[6197,1],[6208,1],[401,1],[6175,1],[5969,1],[6007,4],[5520,1],[5844,1],[6178,0],[6138,3],[6179,2],[6193,0],[6142,3],[5314,2],[6204,0],[6205,0],[6207,0],[6210,3],[6217,0],[6222,0],[6134,0],[6170,0],[6146,1],[6148,1],[6186,1],[5459,1],[6191,1],[6141,1],[6195,1],[6198,2],[5933,3],[6218,1],[6105,1],[6234,1],[6145,4],[5975,1]],"tisk_info":{"tisk_id":208,"obdobi":7,"nazev":"Novela z. o spotřebních daních - EU","konecny_stav":"Schváleno","temata":["Daně - spotřební daň","Evropská unie","Poplatky","Tabák, tabákové výrobky","daň","spotřební daň","tabák","tabákový průmysl"],"historie":["Vláda předložila sněmovně návrh zákona 27. 5. 2014. Zástupce navrhovatele: ministr financí.","Návrh zákona rozeslán poslancům jako tisk 208/0 dne 27. 5. 2014. Návrh zaevidován v systému eKLEP pod čj. OVA 475/14 , PID KORN9GXHEE7B. Navrhovatel navrhl sněmovně projednávání návrhu zákona tak, aby sněmovna s ním mohla vyslovit souhlas již v prvém čtení ( § 90 odstavec 2 zákona č. 90/1995 Sb , o jednacím řádu Poslanecké sněmovny, ve znění pozdějších předpisů).","Organizační výbor projednání návrhu zákona doporučil 29. 5. 2014 (usnesení č. 67 ). Určil zpravodaje: Ing. Ladislav Šincl a navrhl přikázat k projednání výborům: Rozpočtový výbor","1. Čtení Návrh projednán v obecné rozpravě 10. 6. 2014 na 10. schůzi. Sněmovna nesouhlasila s projednáváním tak, aby mohla s návrhem zákona vyslovit souhlas již v prvém čtení. Čtení proběhlo 10. 6. 2014 na 10. schůzi. Návrh zákona přikázán k projednání výborům (usnesení č. 284 ).","Projednávání proběhlo 20. 6. 2014 na 11. schůzi. Lhůta pro projednání výbory byla zkrácena o 30 dní (usnesení č. 358 ).","Rozpočtový výbor projednal návrh zákona a vydal 2. 7. 2014 usnesení doručené poslancům jako tisk 208/1 (pozměňovací návrhy) . Ústavně právní výbor projednal návrh zákona a vydal 3. 7. 2014 usnesení doručené poslancům jako tisk 208/2 (pozměňovací návrhy) . 2. Čtení Návrh zákona prošel obecnou rozpravou 15. 7. 2014 na 12. schůzi. Návrh zákona prošel podrobnou rozpravou 15. 7. 2014 na 12. schůzi. Lhůta pro zahájení třetího čtení byla změněna na 48 hodin po doručení pozměňovacích, popřípadě jiných návrhů poslancům. Podané pozměňovací návrhy zpracovány jako tisk 208/3 , který byl rozeslán 16. 7. 2014 v 9:29. 3. Čtení proběhlo 23. , 30. 7. 2014 na 12. schůzi. Návrh zákona schválen (hlasování č. 97 , usnesení č. 391 ).","2. Čtení Návrh zákona prošel obecnou rozpravou 15. 7. 2014 na 12. schůzi. Návrh zákona prošel podrobnou rozpravou 15. 7. 2014 na 12. schůzi. Lhůta pro zahájení třetího čtení byla změněna na 48 hodin po doručení pozměňovacích, popřípadě jiných návrhů poslancům. Podané pozměňovací návrhy zpracovány jako tisk 208/3 , který byl rozeslán 16. 7. 2014 v 9:29.","3. Čtení proběhlo 23. , 30. 7. 2014 na 12. schůzi. Návrh zákona schválen (hlasování č. 97 , usnesení č. 391 ).","Poslanecká sněmovna postoupila dne 4. 8. 2014 návrh zákona Senátu jako tisk 327 , dokument 327/0 .","Organizační výbor dne 5. 8. 2014 stanovil garančním výborem Výbor pro hospodářství, zemědělství a dopravu ( ).","Výbor pro hospodářství, zemědělství a dopravu projednal návrh dne 26. 8. 2014 a přijal usnesení č. 251, které bylo rozdáno jako tisk 327/1 ( pozměňovací návrhy ).","Návrh projednán dne 27. 8. 2014 na 24. schůzi Senátu. Senát návrh vrátil sněmovně s pozměňovacími návrhy (usnesení č. 587 ).","Návrh zákona ve znění, ve kterém byl postoupen Senátu rozeslán 28. 8. 2014 poslancům jako tisk 208/4 . Dokument Senátu doručen sněmovně a rozeslán 28. 8. 2014 poslancům jako tisk 208/5 . O návrhu zákona vráceném Senátem hlasováno 10. 9. 2014 na 16. schůzi. Sněmovna zákon přijala (hlasování č. 4 , usnesení č. 397 ).","Zákon doručen prezidentovi k podepsání 10. 9. 2014. Prezident zákon podepsal . Rozhodnutí doručeno do Sněmovny 16. 9. 2014.","Schválený zákon odeslán k publikaci ve Sbírce zákonů 24. 9. 2014."],"souvisejici_tisky":[],"souvisejici_usneseni":[284,358,391,397]}}