{"id":35824,"date":"2004-05-06","title":"Odpovědi členů vlády na písemné interpelace","category_id":null,"vote_summary":{"yes":23,"no":48,"abstain":53,"absent":0,"not_logged":76},"party_breakdown":{"cssd":{"yes":0,"no":42,"abstain":10,"absent":0,"not_logged":18},"ods":{"yes":23,"no":1,"abstain":9,"absent":0,"not_logged":24},"kscm":{"yes":0,"no":1,"abstain":25,"absent":0,"not_logged":15},"kdu-csl":{"yes":0,"no":3,"abstain":7,"absent":0,"not_logged":11},"us-deu":{"yes":0,"no":1,"abstain":2,"absent":0,"not_logged":7},"Nezařazení":{"yes":0,"no":0,"abstain":0,"absent":0,"not_logged":1}},"mps":[[344,1],[349,2],[5342,1],[16,1],[5271,1],[354,4],[5263,1],[209,1],[210,1],[211,2],[39,1],[5297,4],[215,4],[367,1],[5252,1],[218,4],[5298,1],[219,2],[450,4],[220,4],[382,1],[5279,1],[77,1],[386,1],[5316,1],[225,2],[454,2],[5120,1],[226,4],[227,1],[396,2],[230,1],[5317,1],[5276,1],[5269,4],[5283,2],[5254,1],[122,1],[124,4],[5318,1],[5264,4],[5265,1],[5310,1],[234,1],[235,4],[5311,1],[236,1],[237,1],[5299,1],[5255,4],[5319,2],[5320,1],[5288,1],[239,4],[241,1],[419,2],[243,4],[246,4],[247,1],[5266,2],[248,1],[422,1],[249,1],[5292,1],[250,4],[5284,1],[5272,1],[252,4],[196,1],[5294,4],[345,0],[347,0],[348,4],[5280,2],[5256,0],[353,4],[356,0],[357,0],[358,0],[5257,4],[360,4],[5213,0],[5285,0],[261,4],[371,4],[372,0],[374,4],[335,0],[67,4],[378,0],[5375,4],[383,0],[5306,4],[5253,4],[266,0],[5258,4],[5300,4],[110,1],[111,0],[400,4],[401,0],[5259,2],[405,2],[269,4],[406,0],[5281,0],[5277,0],[270,0],[273,0],[275,4],[5273,4],[412,4],[437,4],[277,2],[415,2],[5278,0],[5301,2],[421,2],[244,2],[164,4],[423,0],[280,4],[282,4],[429,4],[430,2],[431,0],[285,4],[5312,2],[5302,4],[312,4],[5260,2],[5295,2],[5270,2],[206,2],[5303,2],[19,4],[5307,2],[5289,2],[5261,2],[31,2],[5267,2],[303,4],[36,2],[304,1],[305,2],[4778,4],[5293,2],[366,4],[379,4],[5321,4],[5313,2],[309,4],[5274,2],[99,2],[5290,2],[5328,2],[310,4],[5308,2],[5322,2],[311,4],[136,2],[5296,4],[5282,2],[5275,2],[425,2],[5268,4],[317,4],[5304,4],[295,4],[333,2],[5291,4],[297,4],[5314,2],[54,4],[377,4],[63,4],[64,1],[390,2],[392,2],[340,4],[5262,2],[143,4],[416,4],[5315,1],[301,2],[420,2],[302,4],[5324,1],[5309,4],[5323,4],[5325,1],[5224,4],[389,2],[403,4],[5305,2],[5287,4],[417,4],[5357,4],[5365,4],[5286,4]],"tisk_info":{"tisk_id":618,"obdobi":4,"nazev":"Interpelace F.Beneše na K.Čermáka ve věci Bytového družstva Kavčí skála Říčany","konecny_stav":"Souhlas s odpovědí","temata":["družstevní dům","družstvo","nucená správa","rozsudek"],"historie":["Autor: Ing. František Beneš , CSc. Úplný název: Písemná interpelace Františka Beneše na ministra spravedlnosti Karla Čermáka ve věci posouzení situace Bytového družstva Kavčí skála Říčany a činnosti správce konkurzní podstaty Adresát: JUDr. Karel Čermák Podáno dne: 2. 2. 2004 Odesláno adresátovi: 4. 2. 2004 O zařazení na schůzi požádáno dne: 31. 3. 2004","Rozesláno všem poslancům: 1. 4. 2004 jako tisk 618/0 .","Interpelace projednána dne: 6. 5. 2004 na 31. schůzi Sněmovna vyslovila s odpovědí souhlas (usnesení č. 1126 )."],"souvisejici_tisky":[],"souvisejici_usneseni":[1126]}}