{"id":47794,"date":"2008-06-25","title":"Novela zákoníku práce","category_id":null,"vote_summary":{"yes":9,"no":15,"abstain":130,"absent":8,"not_logged":38},"party_breakdown":{"cssd":{"yes":5,"no":0,"abstain":48,"absent":1,"not_logged":16},"ods":{"yes":2,"no":12,"abstain":50,"absent":4,"not_logged":13},"kscm":{"yes":2,"no":0,"abstain":19,"absent":2,"not_logged":3},"kdu-csl":{"yes":0,"no":2,"abstain":9,"absent":0,"not_logged":2},"sz":{"yes":0,"no":0,"abstain":4,"absent":0,"not_logged":2},"Nezařazení":{"yes":0,"no":1,"abstain":0,"absent":1,"not_logged":2}},"mps":[[344,2],[5444,2],[5447,2],[5342,2],[5383,4],[5451,2],[354,2],[5452,2],[5263,4],[5454,2],[5456,2],[5457,4],[5458,2],[363,2],[5462,4],[5297,4],[5465,2],[5402,4],[218,0],[5298,2],[5469,2],[68,2],[5471,2],[5562,0],[5279,2],[5472,4],[5385,2],[386,4],[5407,2],[5474,0],[5475,2],[5477,2],[396,2],[5414,2],[5482,2],[5317,4],[5485,2],[5486,2],[122,3],[5384,2],[410,2],[5487,2],[5490,2],[5318,4],[5406,2],[5265,4],[5310,2],[235,2],[5311,2],[237,2],[5503,0],[5504,2],[5255,4],[5320,4],[5507,2],[239,0],[5508,2],[419,4],[5513,2],[5514,2],[422,4],[5517,2],[5292,2],[5519,2],[250,2],[5272,2],[252,2],[5415,4],[5522,2],[5294,2],[345,2],[5379,2],[4,2],[5445,1],[5446,2],[5256,0],[5448,2],[5450,2],[5453,2],[5455,2],[356,4],[5257,2],[360,2],[5459,1],[5460,4],[1296,2],[5285,1],[5463,2],[261,1],[5464,1],[371,3],[372,4],[375,0],[374,2],[5468,2],[335,2],[67,2],[5470,2],[5375,1],[383,2],[5306,4],[5473,2],[266,4],[5476,2],[5478,2],[5479,2],[5481,2],[5258,2],[5300,2],[5483,4],[5484,2],[111,2],[401,4],[5259,2],[269,2],[406,2],[5277,4],[5488,2],[273,1],[5489,2],[275,1],[5492,1],[5273,2],[5493,2],[5495,2],[5496,2],[5497,1],[5498,3],[5499,2],[5500,4],[437,2],[277,3],[5378,2],[5501,1],[415,4],[5278,2],[5505,2],[5301,2],[5509,2],[5510,2],[5511,1],[5512,2],[421,4],[5376,2],[164,4],[5515,3],[5516,2],[280,2],[5520,2],[282,2],[430,4],[5302,2],[312,3],[5295,2],[5270,3],[5307,2],[5261,2],[31,4],[5267,2],[303,2],[305,2],[4778,0],[5461,4],[366,2],[5321,2],[5313,2],[309,0],[5274,2],[5290,2],[5328,2],[5308,2],[5322,2],[5502,2],[5282,4],[5506,2],[4527,2],[5268,2],[295,4],[5449,2],[5291,2],[5314,2],[377,2],[64,2],[390,2],[340,2],[143,2],[416,4],[5326,2],[301,1],[420,1],[441,2],[5466,2],[5467,2],[5480,4],[5494,4],[5523,2],[230,1],[5491,4],[236,4],[5521,3]],"tisk_info":{"tisk_id":168,"obdobi":5,"nazev":"Novela z. o vinohradnictví a vinařství","konecny_stav":"Schváleno","temata":["Vinohradnictví a vinařství","Národní hospodářství","Těžba a výroba","půjčka","subvence na úhradu úroků","vinice","víno","vinohradnictví"],"historie":["Skupina poslanců předložila sněmovně návrh zákona 14. 3. 2007. Zástupce navrhovatele: Hašek Michal a další.","Návrh zákona rozeslán poslancům jako tisk 168/0 dne 15. 3. 2007. Navrhovatel navrhl sněmovně projednávání návrhu zákona tak, aby sněmovna s ním mohla vyslovit souhlas již v prvém čtení ( § 90 odstavec 2 zákona č. 90/1995 Sb , o jednacím řádu Poslanecké sněmovny, ve znění pozdějších předpisů).","Návrh zaslán vládě k vyjádření stanoviska 16. 3. 2007. Vláda zaslala stanovisko 12. 4. 2007. Stanovisko vlády rozesláno poslancům 12. 4. 2007 jako tisk 168/1 ( nesouhlas ).","Organizační výbor projednání návrhu zákona doporučil 12. 4. 2007 (usnesení č. 104 ). Určil zpravodaje: Zdeněk Mach a navrhl přikázat k projednání výborům: Zemědělský výbor","1. Čtení Návrh byl projednán v obecné rozpravě 25. 4. 2007 na 14. schůzi. Sněmovna nesouhlasila s projednáváním tak, aby mohla s návrhem zákona vyslovit souhlas již v prvém čtení. Projednávání pokračovalo 25. 4. 2007 na 14. schůzi. Návrh zákona přikázán k projednání výborům (usnesení č. 276 ).","Zemědělský výbor projednal návrh zákona a vydal 20. 5. 2008 usnesení doručené poslancům jako tisk 168/2 (komplexní pozměňující návrh) .","2. Čtení Návrh zákona prošel obecnou rozpravou 5. 6. 2008 na 32. schůzi. Návrh zákona prošel podrobnou rozpravou 5. 6. 2008 na 32. schůzi. Podané pozměňovací návrhy zpracovány jako tisk 168/3 , který byl rozeslán 6. 6. 2008 v 11:30.","3. Čtení proběhlo 25. 6. 2008 na 32. schůzi. Návrh zákona schválen (hlasování č. 206 , usnesení č. 827 ).","Poslanecká sněmovna postoupila dne 2. 7. 2008 návrh zákona Senátu jako tisk 277 , dokument 277/0 .","Organizační výbor dne 2. 7. 2008 stanovil garančním výborem Výbor pro hospodářství, zemědělství a dopravu ( ).","Výbor pro hospodářství, zemědělství a dopravu projednal návrh dne 15. 7. 2008 a přijal usnesení č. 300, které bylo rozdáno jako tisk 277/1 ( schvaluje ).","Návrh projednán dne 17. 7. 2008 na 15. schůzi Senátu. Senát návrh schválil (usnesení č. 466 ).","Zákon doručen prezidentovi k podepsání 28. 7. 2008. Prezident zákon podepsal . Rozhodnutí doručeno do Sněmovny 6. 8. 2008.","Schválený zákon odeslán k publikaci ve Sbírce zákonů 12. 8. 2008."],"souvisejici_tisky":[],"souvisejici_usneseni":[276,827]}}