{"id":25104,"date":"2001-04-12","title":"35. schůze, 268. hlasování , 12. dubna 2001, 11:06:00","category_id":null,"vote_summary":{"yes":162,"no":3,"abstain":7,"absent":0,"not_logged":28},"party_breakdown":{"ods":{"yes":54,"no":0,"abstain":2,"absent":0,"not_logged":7},"kdu-csl":{"yes":14,"no":0,"abstain":1,"absent":0,"not_logged":5},"cssd":{"yes":64,"no":0,"abstain":2,"absent":0,"not_logged":8},"kscm":{"yes":19,"no":0,"abstain":2,"absent":0,"not_logged":3},"us":{"yes":11,"no":3,"abstain":0,"absent":0,"not_logged":4},"Nezařazení":{"yes":0,"no":0,"abstain":0,"absent":0,"not_logged":1}},"mps":[[345,0],[4,0],[347,0],[348,0],[350,0],[352,0],[353,0],[356,0],[357,0],[358,0],[359,0],[360,0],[5213,0],[365,0],[261,0],[369,0],[371,0],[372,0],[375,0],[374,0],[335,0],[67,0],[263,4],[5214,0],[378,0],[69,0],[383,2],[384,0],[385,0],[387,4],[391,0],[266,4],[107,0],[110,0],[111,0],[400,0],[401,0],[402,4],[405,0],[269,0],[406,0],[407,4],[127,4],[409,0],[270,0],[273,0],[275,0],[412,0],[277,0],[415,0],[418,2],[278,0],[421,0],[244,0],[164,4],[423,0],[280,0],[282,0],[429,0],[430,0],[431,0],[432,0],[285,0],[295,4],[333,0],[457,0],[297,0],[54,0],[377,4],[63,0],[64,4],[390,0],[392,2],[399,0],[340,4],[143,4],[416,0],[156,0],[301,0],[420,0],[302,0],[165,0],[193,0],[344,0],[8,0],[349,0],[12,0],[351,4],[16,4],[203,0],[354,0],[208,0],[355,0],[209,4],[210,0],[211,0],[35,0],[362,0],[213,0],[39,0],[40,0],[363,2],[214,0],[215,0],[367,0],[370,0],[217,0],[218,0],[376,0],[219,0],[220,4],[222,0],[382,0],[77,0],[386,4],[388,0],[224,0],[225,0],[226,0],[393,0],[227,0],[229,0],[396,0],[5193,0],[122,0],[124,0],[410,0],[411,0],[232,0],[233,0],[234,0],[235,0],[236,0],[237,0],[413,0],[414,0],[239,0],[240,0],[241,4],[419,0],[242,0],[243,0],[245,0],[246,0],[247,0],[248,0],[422,0],[249,0],[424,2],[250,0],[426,0],[427,0],[428,0],[252,0],[196,0],[253,4],[254,4],[312,0],[206,0],[19,0],[31,0],[303,4],[361,0],[36,0],[304,0],[305,0],[366,0],[306,4],[307,0],[308,0],[379,0],[309,2],[99,2],[310,0],[105,0],[311,0],[136,0],[313,4],[162,0],[425,0],[317,0],[364,1],[380,1],[381,0],[79,4],[389,0],[91,0],[395,0],[397,0],[368,4],[398,0],[403,0],[404,0],[408,4],[129,0],[272,1],[417,0],[181,4],[185,0],[394,4]],"tisk_info":{"tisk_id":828,"obdobi":3,"nazev":"Návrh zák. o majetku ČR a jejím vystup. v právních vztazích","konecny_stav":"Schváleno","temata":["Vztahy vlastnické","nemovitý majetek","převod vlastnictví","půda ve vlastnictví státu","veřejný majetek"],"historie":["Skupina poslanců ( Zdeňka Horníková , Pavel Hrnčíř , Vladimír Doležal , Pavel Němec , Evžen Snítilý , Stanislav Křeček ) předložila sněmovně návrh zákona 30. 1. 2001. Zástupce navrhovatele: Horníková Zdeňka a další.","Návrh zákona rozeslán poslancům jako tisk 828/0 dne 1. 2. 2001.","Návrh zaslán vládě k vyjádření stanoviska 1. 2. 2001. Vláda zaslala stanovisko 28. 2. 2001. Stanovisko vlády rozesláno poslancům 1. 3. 2001 jako tisk 828/1 ( připomínky ).","Organizační výbor projednání návrhu zákona doporučil 15. 3. 2001 (usnesení č. 383 ). Určil zpravodaje: Evžen Snítilý a navrhl přikázat k projednání výborům: Ústavně právní výbor , Výbor pro veřejnou správu, regionální rozvoj a životní prostředí","1. Čtení proběhlo 3. 4. 2001 na 35. schůzi. Návrh zákona přikázán k projednání výborům (usnesení č. 1500 ). Lhůta k projednání výbory byla určena na 5 dní .","Výbor pro veřejnou správu, regionální rozvoj a životní prostředí projednal návrh zákona a vydal 11. 4. 2001 usnesení doručené poslancům jako tisk 828/2 . Výbor pro veřejnou správu, regionální rozvoj a životní prostředí vydal 11. 4. 2001 oponentní zprávu jako tisk 828/3 .","2. Čtení Návrh zákona v obecné rozpravě 12. 4. 2001 na 35. schůzi vrácen výborům k novému projednání (hlasování č. 268 , usnesení č. 1551 ).","Výbor pro veřejnou správu, regionální rozvoj a životní prostředí projednal návrh zákona a vydal 11. 5. 2001 usnesení doručené poslancům jako tisk 828/4 . Hospodářský výbor projednal navíc návrh zákona a vydal 14. 5. 2001 usnesení doručené poslancům jako tisk 828/5 . Ústavně právní výbor projednal navíc návrh zákona a vydal 16. 5. 2001 usnesení doručené poslancům jako tisk 828/6 . 2. Čtení Návrh zákona prošel obecnou rozpravou 22. 5. 2001 na 36. schůzi. Návrh zákona prošel podrobnou rozpravou 22. 5. 2001 na 36. schůzi. Podané pozměňovací návrhy zpracovány jako tisk 828/7 , který byl rozeslán 23. 5. 2001 v 12:00. 3. Čtení proběhlo 25. 5. 2001 na 36. schůzi. Návrh zákona schválen (hlasování č. 491 , usnesení č. 1622 ).","2. Čtení Návrh zákona prošel obecnou rozpravou 22. 5. 2001 na 36. schůzi. Návrh zákona prošel podrobnou rozpravou 22. 5. 2001 na 36. schůzi. Podané pozměňovací návrhy zpracovány jako tisk 828/7 , který byl rozeslán 23. 5. 2001 v 12:00.","3. Čtení proběhlo 25. 5. 2001 na 36. schůzi. Návrh zákona schválen (hlasování č. 491 , usnesení č. 1622 ).","Poslanecká sněmovna postoupila dne 14. 10. 2002 návrh zákona Senátu jako tisk 59 , dokument 59/0 .","Organizační výbor dne 14. 10. 2002 stanovil garančním výborem Výbor pro hospodářství, zemědělství a dopravu ( ) a přikázal tisk k projednání: Ústavně-právní výbor ( ), Výbor pro územní rozvoj, veřejnou správu a životní prostředí ( ).","Výbor pro hospodářství, zemědělství a dopravu projednal návrh dne 6. 6. 2001 a přijal usnesení č. 70, které bylo rozdáno jako tisk 59/1 ( schvaluje ). Ústavně-právní výbor projednal návrh dne 6. 6. 2001 a přijal usnesení č. 34, které bylo rozdáno jako tisk 59/2 ( nezabývat se ). Výbor pro územní rozvoj, veřejnou správu a životní prostředí projednal návrh dne 13. 6. 2001 a přijal usnesení č. 32, které bylo rozdáno jako tisk 59/3 ( schvaluje ).","Zákon doručen prezidentovi k podepsání 15. 6. 2001. Prezident zákon podepsal . Rozhodnutí doručeno do Sněmovny 26. 6. 2001.","Schválený zákon odeslán k publikaci ve Sbírce zákonů 26. 6. 2001."],"souvisejici_tisky":[],"souvisejici_usneseni":[1500,1551,1622]}}